pyicom/__init__.py
pyicom/client.py
pyicom/common.py
pyicom/server.py
pyicom-0.1.1.dist-info/METADATA
pyicom-0.1.1.dist-info/WHEEL
pyicom-0.1.1.dist-info/top_level.txt
pyicom-0.1.1.dist-info/RECORD
